{
    "data": [
        {
            "id": "6133",
            "name": "Caterpie",
            "nomePt": "",
            "collectionId": "smm-j",
            "supertypeId": 1,
            "rarityId": 10,
            "artistId": 172,
            "hp": 60,
            "number": "",
            "numberInt": 1,
            "smallImage": "https://static.tcgcollector.com/content/images/53/e3/b1/53e3b1b4bc1d4967ef3e527fcf061b820f819cbe84a87100a07a79c3a1cf75dd.jpg",
            "largeImage": "https://static.tcgcollector.com/content/images/53/e3/b1/53e3b1b4bc1d4967ef3e527fcf061b820f819cbe84a87100a07a79c3a1cf75dd.jpg",
            "nameClear": "",
            "numeroLiga": "(1/51)",
            "codigoLiga": "caterpie (1/51)",
            "myp": "",
            "language": "ja",
            "regulationMark": "",
            "retreatCost": 0
        },
        {
            "id": "6134",
            "name": "Metapod",
            "nomePt": "",
            "collectionId": "smm-j",
            "supertypeId": 1,
            "rarityId": 10,
            "artistId": 163,
            "hp": 90,
            "number": "",
            "numberInt": 2,
            "smallImage": "https://static.tcgcollector.com/content/images/b5/c3/21/b5c3211f56ac4785d29afe24e551d1bf92bd1707cece7d5f6a68199f56801bcd.jpg",
            "largeImage": "https://static.tcgcollector.com/content/images/b5/c3/21/b5c3211f56ac4785d29afe24e551d1bf92bd1707cece7d5f6a68199f56801bcd.jpg",
            "nameClear": "",
            "numeroLiga": "(2/51)",
            "codigoLiga": "metapod (2/51)",
            "myp": "",
            "language": "ja",
            "regulationMark": "",
            "retreatCost": 0
        },
        {
            "id": "6135",
            "name": "Butterfree",
            "nomePt": "",
            "collectionId": "smm-j",
            "supertypeId": 1,
            "rarityId": 10,
            "artistId": 71,
            "hp": 130,
            "number": "",
            "numberInt": 3,
            "smallImage": "https://static.tcgcollector.com/content/images/de/a3/c5/dea3c5ebd41558ee90d6b4384bf2fb9c36b2cfad8ec494624bc35caa2172f2a7.jpg",
            "largeImage": "https://static.tcgcollector.com/content/images/de/a3/c5/dea3c5ebd41558ee90d6b4384bf2fb9c36b2cfad8ec494624bc35caa2172f2a7.jpg",
            "nameClear": "",
            "numeroLiga": "(3/51)",
            "codigoLiga": "butterfree (3/51)",
            "myp": "",
            "language": "ja",
            "regulationMark": "",
            "retreatCost": 0
        },
        {
            "id": "6136",
            "name": "Scyther",
            "nomePt": "",
            "collectionId": "smm-j",
            "supertypeId": 1,
            "rarityId": 10,
            "artistId": 153,
            "hp": 100,
            "number": "",
            "numberInt": 4,
            "smallImage": "https://static.tcgcollector.com/content/images/44/cf/4f/44cf4f6c61e931ab92f6adcf6d150dc30499077a2019e5e6e8193a194c3bdd0f.jpg",
            "largeImage": "https://static.tcgcollector.com/content/images/44/cf/4f/44cf4f6c61e931ab92f6adcf6d150dc30499077a2019e5e6e8193a194c3bdd0f.jpg",
            "nameClear": "",
            "numeroLiga": "(4/51)",
            "codigoLiga": "scyther (4/51)",
            "myp": "",
            "language": "ja",
            "regulationMark": "",
            "retreatCost": 0
        },
        {
            "id": "6137",
            "name": "Pinsir-GX",
            "nomePt": "",
            "collectionId": "smm-j",
            "supertypeId": 1,
            "rarityId": 10,
            "artistId": 131,
            "hp": 180,
            "number": "",
            "numberInt": 5,
            "smallImage": "https://static.tcgcollector.com/content/images/2d/0d/78/2d0d782c75a2e9eec62ec9b22e23d8980f3cea951fad479f1c35c4686aee88a4.jpg",
            "largeImage": "https://static.tcgcollector.com/content/images/2d/0d/78/2d0d782c75a2e9eec62ec9b22e23d8980f3cea951fad479f1c35c4686aee88a4.jpg",
            "nameClear": "",
            "numeroLiga": "(5/51)",
            "codigoLiga": "pinsir-gx (5/51)",
            "myp": "",
            "language": "ja",
            "regulationMark": "",
            "retreatCost": 0
        },
        {
            "id": "6138",
            "name": "Dhelmise",
            "nomePt": "",
            "collectionId": "smm-j",
            "supertypeId": 1,
            "rarityId": 10,
            "artistId": 107,
            "hp": 100,
            "number": "",
            "numberInt": 6,
            "smallImage": "https://static.tcgcollector.com/content/images/31/02/f4/3102f4a13181a4b01e80100d2043fd74d717d73fb3cb43da467f2dd599a86efb.jpg",
            "largeImage": "https://static.tcgcollector.com/content/images/31/02/f4/3102f4a13181a4b01e80100d2043fd74d717d73fb3cb43da467f2dd599a86efb.jpg",
            "nameClear": "",
            "numeroLiga": "(6/51)",
            "codigoLiga": "dhelmise (6/51)",
            "myp": "",
            "language": "ja",
            "regulationMark": "",
            "retreatCost": 0
        },
        {
            "id": "6139",
            "name": "Charmander",
            "nomePt": "",
            "collectionId": "smm-j",
            "supertypeId": 1,
            "rarityId": 10,
            "artistId": 137,
            "hp": 70,
            "number": "",
            "numberInt": 7,
            "smallImage": "https://static.tcgcollector.com/content/images/02/6d/52/026d52f5b6819bf60e7b7b23792204dc15a2fded73a1aa8555147e3c8c9c1833.jpg",
            "largeImage": "https://static.tcgcollector.com/content/images/02/6d/52/026d52f5b6819bf60e7b7b23792204dc15a2fded73a1aa8555147e3c8c9c1833.jpg",
            "nameClear": "",
            "numeroLiga": "(7/51)",
            "codigoLiga": "charmander (7/51)",
            "myp": "",
            "language": "ja",
            "regulationMark": "",
            "retreatCost": 0
        },
        {
            "id": "6140",
            "name": "Charmeleon",
            "nomePt": "",
            "collectionId": "smm-j",
            "supertypeId": 1,
            "rarityId": 10,
            "artistId": 106,
            "hp": 100,
            "number": "",
            "numberInt": 8,
            "smallImage": "https://static.tcgcollector.com/content/images/de/cd/b4/decdb4ecfe98c21c0ddc5eaea056995a5c1220bd8e3eae7209a911c688b19be6.jpg",
            "largeImage": "https://static.tcgcollector.com/content/images/de/cd/b4/decdb4ecfe98c21c0ddc5eaea056995a5c1220bd8e3eae7209a911c688b19be6.jpg",
            "nameClear": "",
            "numeroLiga": "(8/51)",
            "codigoLiga": "charmeleon (8/51)",
            "myp": "",
            "language": "ja",
            "regulationMark": "",
            "retreatCost": 0
        },
        {
            "id": "6141",
            "name": "Charizard-GX",
            "nomePt": "",
            "collectionId": "smm-j",
            "supertypeId": 1,
            "rarityId": 10,
            "artistId": 178,
            "hp": 250,
            "number": "",
            "numberInt": 9,
            "smallImage": "https://static.tcgcollector.com/content/images/7c/30/ff/7c30ff943dd5fee3b3cbfcd050fae641743ff8720701bb9aabd35ffd9816d8d9.jpg",
            "largeImage": "https://static.tcgcollector.com/content/images/7c/30/ff/7c30ff943dd5fee3b3cbfcd050fae641743ff8720701bb9aabd35ffd9816d8d9.jpg",
            "nameClear": "",
            "numeroLiga": "(9/51)",
            "codigoLiga": "charizard-gx (9/51)",
            "myp": "",
            "language": "ja",
            "regulationMark": "",
            "retreatCost": 0
        },
        {
            "id": "6142",
            "name": "Magmar",
            "nomePt": "",
            "collectionId": "smm-j",
            "supertypeId": 1,
            "rarityId": 10,
            "artistId": 142,
            "hp": 90,
            "number": "",
            "numberInt": 10,
            "smallImage": "https://static.tcgcollector.com/content/images/ac/5a/1f/ac5a1fcd40a12971c8a9ccc8df183dacda38e5d75bf8974dcfee155e83f49cf0.jpg",
            "largeImage": "https://static.tcgcollector.com/content/images/ac/5a/1f/ac5a1fcd40a12971c8a9ccc8df183dacda38e5d75bf8974dcfee155e83f49cf0.jpg",
            "nameClear": "",
            "numeroLiga": "(10/51)",
            "codigoLiga": "magmar (10/51)",
            "myp": "",
            "language": "ja",
            "regulationMark": "",
            "retreatCost": 0
        },
        {
            "id": "6143",
            "name": "Salandit",
            "nomePt": "",
            "collectionId": "smm-j",
            "supertypeId": 1,
            "rarityId": 10,
            "artistId": 45,
            "hp": 70,
            "number": "",
            "numberInt": 11,
            "smallImage": "https://static.tcgcollector.com/content/images/69/b9/42/69b9426dd3884f84187f6b2c0ad598e38d37478b2ada083d36c56208655b41fc.jpg",
            "largeImage": "https://static.tcgcollector.com/content/images/69/b9/42/69b9426dd3884f84187f6b2c0ad598e38d37478b2ada083d36c56208655b41fc.jpg",
            "nameClear": "",
            "numeroLiga": "(11/51)",
            "codigoLiga": "salandit (11/51)",
            "myp": "",
            "language": "ja",
            "regulationMark": "",
            "retreatCost": 0
        },
        {
            "id": "6144",
            "name": "Salazzle",
            "nomePt": "",
            "collectionId": "smm-j",
            "supertypeId": 1,
            "rarityId": 10,
            "artistId": 62,
            "hp": 100,
            "number": "",
            "numberInt": 12,
            "smallImage": "https://static.tcgcollector.com/content/images/3d/40/29/3d402921bc40e09102f856b7f31fe38eb051539ae738e711118ee6ef2e7a82cd.jpg",
            "largeImage": "https://static.tcgcollector.com/content/images/3d/40/29/3d402921bc40e09102f856b7f31fe38eb051539ae738e711118ee6ef2e7a82cd.jpg",
            "nameClear": "",
            "numeroLiga": "(12/51)",
            "codigoLiga": "salazzle (12/51)",
            "myp": "",
            "language": "ja",
            "regulationMark": "",
            "retreatCost": 0
        },
        {
            "id": "6145",
            "name": "Psyduck",
            "nomePt": "",
            "collectionId": "smm-j",
            "supertypeId": 1,
            "rarityId": 10,
            "artistId": 156,
            "hp": 60,
            "number": "",
            "numberInt": 13,
            "smallImage": "https://static.tcgcollector.com/content/images/c7/26/b1/c726b1145007f53eb1f2714be1c52c0345b79f066973bc4a50fe3052d2500333.jpg",
            "largeImage": "https://static.tcgcollector.com/content/images/c7/26/b1/c726b1145007f53eb1f2714be1c52c0345b79f066973bc4a50fe3052d2500333.jpg",
            "nameClear": "",
            "numeroLiga": "(13/51)",
            "codigoLiga": "psyduck (13/51)",
            "myp": "",
            "language": "ja",
            "regulationMark": "",
            "retreatCost": 0
        },
        {
            "id": "6146",
            "name": "Magikarp",
            "nomePt": "",
            "collectionId": "smm-j",
            "supertypeId": 1,
            "rarityId": 10,
            "artistId": 127,
            "hp": 30,
            "number": "",
            "numberInt": 14,
            "smallImage": "https://static.tcgcollector.com/content/images/03/9b/79/039b7947c819d2041619e10ec4c16cf70072bc3e6975cbc32facb73f5ef400d3.jpg",
            "largeImage": "https://static.tcgcollector.com/content/images/03/9b/79/039b7947c819d2041619e10ec4c16cf70072bc3e6975cbc32facb73f5ef400d3.jpg",
            "nameClear": "",
            "numeroLiga": "(14/51)",
            "codigoLiga": "magikarp (14/51)",
            "myp": "",
            "language": "ja",
            "regulationMark": "",
            "retreatCost": 0
        },
        {
            "id": "6147",
            "name": "Gyarados-GX",
            "nomePt": "",
            "collectionId": "smm-j",
            "supertypeId": 1,
            "rarityId": 10,
            "artistId": 131,
            "hp": 230,
            "number": "",
            "numberInt": 15,
            "smallImage": "https://static.tcgcollector.com/content/images/10/39/8f/10398fb13103a7d6ecd5f0e89d8e019ea52fdc9889e8a609f128287db081300d.jpg",
            "largeImage": "https://static.tcgcollector.com/content/images/10/39/8f/10398fb13103a7d6ecd5f0e89d8e019ea52fdc9889e8a609f128287db081300d.jpg",
            "nameClear": "",
            "numeroLiga": "(15/51)",
            "codigoLiga": "gyarados-gx (15/51)",
            "myp": "",
            "language": "ja",
            "regulationMark": "",
            "retreatCost": 0
        },
        {
            "id": "6148",
            "name": "Lapras",
            "nomePt": "",
            "collectionId": "smm-j",
            "supertypeId": 1,
            "rarityId": 10,
            "artistId": 161,
            "hp": 120,
            "number": "",
            "numberInt": 16,
            "smallImage": "https://static.tcgcollector.com/content/images/b8/4f/3a/b84f3a3ddf8f44f355d981a385102be827ef24ca6d13e882f9bc7eaf9883abeb.jpg",
            "largeImage": "https://static.tcgcollector.com/content/images/b8/4f/3a/b84f3a3ddf8f44f355d981a385102be827ef24ca6d13e882f9bc7eaf9883abeb.jpg",
            "nameClear": "",
            "numeroLiga": "(16/51)",
            "codigoLiga": "lapras (16/51)",
            "myp": "",
            "language": "ja",
            "regulationMark": "",
            "retreatCost": 0
        },
        {
            "id": "6149",
            "name": "Pyukumuku",
            "nomePt": "",
            "collectionId": "smm-j",
            "supertypeId": 1,
            "rarityId": 10,
            "artistId": 150,
            "hp": 80,
            "number": "",
            "numberInt": 17,
            "smallImage": "https://static.tcgcollector.com/content/images/d9/1e/c2/d91ec253969cf6ee8e2e7dd34b1882b58007c9f5398eaa59ccbb4a542ebe4414.jpg",
            "largeImage": "https://static.tcgcollector.com/content/images/d9/1e/c2/d91ec253969cf6ee8e2e7dd34b1882b58007c9f5398eaa59ccbb4a542ebe4414.jpg",
            "nameClear": "",
            "numeroLiga": "(17/51)",
            "codigoLiga": "pyukumuku (17/51)",
            "myp": "",
            "language": "ja",
            "regulationMark": "",
            "retreatCost": 0
        },
        {
            "id": "6150",
            "name": "Pikachu",
            "nomePt": "",
            "collectionId": "smm-j",
            "supertypeId": 1,
            "rarityId": 10,
            "artistId": 5,
            "hp": 70,
            "number": "",
            "numberInt": 18,
            "smallImage": "https://static.tcgcollector.com/content/images/dc/0d/03/dc0d03d4305df741ea482f442cdf12c3c7f37e51d7f50ed47531c5d0ca7871d8.jpg",
            "largeImage": "https://static.tcgcollector.com/content/images/dc/0d/03/dc0d03d4305df741ea482f442cdf12c3c7f37e51d7f50ed47531c5d0ca7871d8.jpg",
            "nameClear": "",
            "numeroLiga": "(18/51)",
            "codigoLiga": "pikachu (18/51)",
            "myp": "",
            "language": "ja",
            "regulationMark": "",
            "retreatCost": 0
        },
        {
            "id": "6151",
            "name": "Raichu-GX",
            "nomePt": "",
            "collectionId": "smm-j",
            "supertypeId": 1,
            "rarityId": 10,
            "artistId": 131,
            "hp": 210,
            "number": "",
            "numberInt": 19,
            "smallImage": "https://static.tcgcollector.com/content/images/6b/39/b9/6b39b9e761fcab68ea68e9fae19d6ce152ed9d78a5bcabece221edff5e4c1028.jpg",
            "largeImage": "https://static.tcgcollector.com/content/images/6b/39/b9/6b39b9e761fcab68ea68e9fae19d6ce152ed9d78a5bcabece221edff5e4c1028.jpg",
            "nameClear": "",
            "numeroLiga": "(19/51)",
            "codigoLiga": "raichu-gx (19/51)",
            "myp": "",
            "language": "ja",
            "regulationMark": "",
            "retreatCost": 0
        },
        {
            "id": "6152",
            "name": "Voltorb",
            "nomePt": "",
            "collectionId": "smm-j",
            "supertypeId": 1,
            "rarityId": 10,
            "artistId": 189,
            "hp": 50,
            "number": "",
            "numberInt": 20,
            "smallImage": "https://static.tcgcollector.com/content/images/e7/67/79/e767793ea85d6b397092352082a7e769ef2c2c0832ae9b0e28f9d31ae8320ca5.jpg",
            "largeImage": "https://static.tcgcollector.com/content/images/e7/67/79/e767793ea85d6b397092352082a7e769ef2c2c0832ae9b0e28f9d31ae8320ca5.jpg",
            "nameClear": "",
            "numeroLiga": "(20/51)",
            "codigoLiga": "voltorb (20/51)",
            "myp": "",
            "language": "ja",
            "regulationMark": "",
            "retreatCost": 0
        },
        {
            "id": "6153",
            "name": "Electrode",
            "nomePt": "",
            "collectionId": "smm-j",
            "supertypeId": 1,
            "rarityId": 10,
            "artistId": 167,
            "hp": 100,
            "number": "",
            "numberInt": 21,
            "smallImage": "https://static.tcgcollector.com/content/images/58/07/e9/5807e95e71e82df42be562a4a2675b97617c3588ddab5aedcfb9a7752056742b.jpg",
            "largeImage": "https://static.tcgcollector.com/content/images/58/07/e9/5807e95e71e82df42be562a4a2675b97617c3588ddab5aedcfb9a7752056742b.jpg",
            "nameClear": "",
            "numeroLiga": "(21/51)",
            "codigoLiga": "electrode (21/51)",
            "myp": "",
            "language": "ja",
            "regulationMark": "",
            "retreatCost": 0
        },
        {
            "id": "6154",
            "name": "Togedemaru",
            "nomePt": "",
            "collectionId": "smm-j",
            "supertypeId": 1,
            "rarityId": 10,
            "artistId": 171,
            "hp": 70,
            "number": "",
            "numberInt": 22,
            "smallImage": "https://static.tcgcollector.com/content/images/c2/b9/aa/c2b9aa872d968128f7b81fd55f8a3323e19b92b431f2ae94ce99c6ed103e82a4.jpg",
            "largeImage": "https://static.tcgcollector.com/content/images/c2/b9/aa/c2b9aa872d968128f7b81fd55f8a3323e19b92b431f2ae94ce99c6ed103e82a4.jpg",
            "nameClear": "",
            "numeroLiga": "(22/51)",
            "codigoLiga": "togedemaru (22/51)",
            "myp": "",
            "language": "ja",
            "regulationMark": "",
            "retreatCost": 0
        },
        {
            "id": "6155",
            "name": "Ekans",
            "nomePt": "",
            "collectionId": "smm-j",
            "supertypeId": 1,
            "rarityId": 10,
            "artistId": 116,
            "hp": 60,
            "number": "",
            "numberInt": 23,
            "smallImage": "https://static.tcgcollector.com/content/images/13/14/02/131402dc66a55e893485f0b61267cb51a67c16b8cbd686b27cb7be3e9db9a4d0.jpg",
            "largeImage": "https://static.tcgcollector.com/content/images/13/14/02/131402dc66a55e893485f0b61267cb51a67c16b8cbd686b27cb7be3e9db9a4d0.jpg",
            "nameClear": "",
            "numeroLiga": "(23/51)",
            "codigoLiga": "ekans (23/51)",
            "myp": "",
            "language": "ja",
            "regulationMark": "",
            "retreatCost": 0
        },
        {
            "id": "6156",
            "name": "Jynx",
            "nomePt": "",
            "collectionId": "smm-j",
            "supertypeId": 1,
            "rarityId": 10,
            "artistId": 61,
            "hp": 100,
            "number": "",
            "numberInt": 24,
            "smallImage": "https://static.tcgcollector.com/content/images/6c/ec/9f/6cec9fe07f8161d085a1624de9fa7b34a94d2f3a34dc0e44aa4a55c876b114be.jpg",
            "largeImage": "https://static.tcgcollector.com/content/images/6c/ec/9f/6cec9fe07f8161d085a1624de9fa7b34a94d2f3a34dc0e44aa4a55c876b114be.jpg",
            "nameClear": "",
            "numeroLiga": "(24/51)",
            "codigoLiga": "jynx (24/51)",
            "myp": "",
            "language": "ja",
            "regulationMark": "",
            "retreatCost": 0
        },
        {
            "id": "6157",
            "name": "Mewtwo-GX",
            "nomePt": "",
            "collectionId": "smm-j",
            "supertypeId": 1,
            "rarityId": 10,
            "artistId": 178,
            "hp": 180,
            "number": "",
            "numberInt": 25,
            "smallImage": "https://static.tcgcollector.com/content/images/d3/42/48/d34248ef1148814e098276cc65fc630c63bb1cdd1b91422560a88e6f07b98ef6.jpg",
            "largeImage": "https://static.tcgcollector.com/content/images/d3/42/48/d34248ef1148814e098276cc65fc630c63bb1cdd1b91422560a88e6f07b98ef6.jpg",
            "nameClear": "",
            "numeroLiga": "(25/51)",
            "codigoLiga": "mewtwo-gx (25/51)",
            "myp": "",
            "language": "ja",
            "regulationMark": "",
            "retreatCost": 0
        },
        {
            "id": "6158",
            "name": "Mew",
            "nomePt": "",
            "collectionId": "smm-j",
            "supertypeId": 1,
            "rarityId": 10,
            "artistId": 12,
            "hp": 80,
            "number": "",
            "numberInt": 26,
            "smallImage": "https://static.tcgcollector.com/content/images/f8/0e/05/f80e056e193dbce6fb8f752d4c7aca14384685c67f7bd82b5f61c9ddbad77c3c.jpg",
            "largeImage": "https://static.tcgcollector.com/content/images/f8/0e/05/f80e056e193dbce6fb8f752d4c7aca14384685c67f7bd82b5f61c9ddbad77c3c.jpg",
            "nameClear": "",
            "numeroLiga": "(26/51)",
            "codigoLiga": "mew (26/51)",
            "myp": "",
            "language": "ja",
            "regulationMark": "",
            "retreatCost": 0
        },
        {
            "id": "6159",
            "name": "Mareanie",
            "nomePt": "",
            "collectionId": "smm-j",
            "supertypeId": 1,
            "rarityId": 10,
            "artistId": 103,
            "hp": 70,
            "number": "",
            "numberInt": 27,
            "smallImage": "https://static.tcgcollector.com/content/images/46/58/0a/46580a8c4284c2bcc935a41df13a07049af686d5ec617343c4da8c98966d19f7.jpg",
            "largeImage": "https://static.tcgcollector.com/content/images/46/58/0a/46580a8c4284c2bcc935a41df13a07049af686d5ec617343c4da8c98966d19f7.jpg",
            "nameClear": "",
            "numeroLiga": "(27/51)",
            "codigoLiga": "mareanie (27/51)",
            "myp": "",
            "language": "ja",
            "regulationMark": "",
            "retreatCost": 0
        },
        {
            "id": "6160",
            "name": "Toxapex",
            "nomePt": "",
            "collectionId": "smm-j",
            "supertypeId": 1,
            "rarityId": 10,
            "artistId": 151,
            "hp": 110,
            "number": "",
            "numberInt": 28,
            "smallImage": "https://static.tcgcollector.com/content/images/30/58/2d/30582d3ed74a303b7f5615ed843562eb8bba9c02d1a79aae91f6f254323edee2.jpg",
            "largeImage": "https://static.tcgcollector.com/content/images/30/58/2d/30582d3ed74a303b7f5615ed843562eb8bba9c02d1a79aae91f6f254323edee2.jpg",
            "nameClear": "",
            "numeroLiga": "(28/51)",
            "codigoLiga": "toxapex (28/51)",
            "myp": "",
            "language": "ja",
            "regulationMark": "",
            "retreatCost": 0
        },
        {
            "id": "6161",
            "name": "Clefairy",
            "nomePt": "",
            "collectionId": "smm-j",
            "supertypeId": 1,
            "rarityId": 10,
            "artistId": 147,
            "hp": 60,
            "number": "",
            "numberInt": 29,
            "smallImage": "https://static.tcgcollector.com/content/images/1b/90/45/1b90455b48094d0c00113e2daf78786c3631a23da909f9c58743be7b0378f15f.jpg",
            "largeImage": "https://static.tcgcollector.com/content/images/1b/90/45/1b90455b48094d0c00113e2daf78786c3631a23da909f9c58743be7b0378f15f.jpg",
            "nameClear": "",
            "numeroLiga": "(29/51)",
            "codigoLiga": "clefairy (29/51)",
            "myp": "",
            "language": "ja",
            "regulationMark": "",
            "retreatCost": 0
        },
        {
            "id": "6162",
            "name": "Clefable",
            "nomePt": "",
            "collectionId": "smm-j",
            "supertypeId": 1,
            "rarityId": 10,
            "artistId": 109,
            "hp": 120,
            "number": "",
            "numberInt": 30,
            "smallImage": "https://static.tcgcollector.com/content/images/fd/f0/81/fdf0810e40e5097c8bf5fac84cdd085d1a7328325e866c4fc3b96fb740db1220.jpg",
            "largeImage": "https://static.tcgcollector.com/content/images/fd/f0/81/fdf0810e40e5097c8bf5fac84cdd085d1a7328325e866c4fc3b96fb740db1220.jpg",
            "nameClear": "",
            "numeroLiga": "(30/51)",
            "codigoLiga": "clefable (30/51)",
            "myp": "",
            "language": "ja",
            "regulationMark": "",
            "retreatCost": 0
        },
        {
            "id": "6163",
            "name": "Jigglypuff",
            "nomePt": "",
            "collectionId": "smm-j",
            "supertypeId": 1,
            "rarityId": 10,
            "artistId": 129,
            "hp": 70,
            "number": "",
            "numberInt": 31,
            "smallImage": "https://static.tcgcollector.com/content/images/f0/6e/c6/f06ec66186cd9952ad0ecb4eec6b6ff08148e77dc0cc907f08bd83aaaa84d188.jpg",
            "largeImage": "https://static.tcgcollector.com/content/images/f0/6e/c6/f06ec66186cd9952ad0ecb4eec6b6ff08148e77dc0cc907f08bd83aaaa84d188.jpg",
            "nameClear": "",
            "numeroLiga": "(31/51)",
            "codigoLiga": "jigglypuff (31/51)",
            "myp": "",
            "language": "ja",
            "regulationMark": "",
            "retreatCost": 0
        },
        {
            "id": "6164",
            "name": "Wigglytuff-GX",
            "nomePt": "",
            "collectionId": "smm-j",
            "supertypeId": 1,
            "rarityId": 10,
            "artistId": 131,
            "hp": 210,
            "number": "",
            "numberInt": 32,
            "smallImage": "https://static.tcgcollector.com/content/images/1b/95/87/1b958791df05543c76f3496d13022ec2de8d35f9caaa17666e310782cd703b2e.jpg",
            "largeImage": "https://static.tcgcollector.com/content/images/1b/95/87/1b958791df05543c76f3496d13022ec2de8d35f9caaa17666e310782cd703b2e.jpg",
            "nameClear": "",
            "numeroLiga": "(32/51)",
            "codigoLiga": "wigglytuff-gx (32/51)",
            "myp": "",
            "language": "ja",
            "regulationMark": "",
            "retreatCost": 0
        },
        {
            "id": "6165",
            "name": "Mr. Mime",
            "nomePt": "",
            "collectionId": "smm-j",
            "supertypeId": 1,
            "rarityId": 10,
            "artistId": 160,
            "hp": 90,
            "number": "",
            "numberInt": 33,
            "smallImage": "https://static.tcgcollector.com/content/images/ea/f6/80/eaf680a81356079494210df6b6e842a8575b59153963f52eeae6f6131a16f3e9.jpg",
            "largeImage": "https://static.tcgcollector.com/content/images/ea/f6/80/eaf680a81356079494210df6b6e842a8575b59153963f52eeae6f6131a16f3e9.jpg",
            "nameClear": "",
            "numeroLiga": "(33/51)",
            "codigoLiga": "mr. mime (33/51)",
            "myp": "",
            "language": "ja",
            "regulationMark": "",
            "retreatCost": 0
        },
        {
            "id": "6166",
            "name": "Farfetch'd",
            "nomePt": "",
            "collectionId": "smm-j",
            "supertypeId": 1,
            "rarityId": 10,
            "artistId": 164,
            "hp": 80,
            "number": "",
            "numberInt": 34,
            "smallImage": "https://static.tcgcollector.com/content/images/11/f9/d2/11f9d227009a71d7291d995e3b80e3db832510f11e6b3f414799c4d7a55d07ab.jpg",
            "largeImage": "https://static.tcgcollector.com/content/images/11/f9/d2/11f9d227009a71d7291d995e3b80e3db832510f11e6b3f414799c4d7a55d07ab.jpg",
            "nameClear": "",
            "numeroLiga": "(34/51)",
            "codigoLiga": "farfetch'd (34/51)",
            "myp": "",
            "language": "ja",
            "regulationMark": "",
            "retreatCost": 0
        },
        {
            "id": "6167",
            "name": "Chansey",
            "nomePt": "",
            "collectionId": "smm-j",
            "supertypeId": 1,
            "rarityId": 10,
            "artistId": 193,
            "hp": 130,
            "number": "",
            "numberInt": 35,
            "smallImage": "https://static.tcgcollector.com/content/images/87/f3/24/87f3244f3c5f350faa267d5e656320dd345f02fadf6a05f69a6029ff277d1071.jpg",
            "largeImage": "https://static.tcgcollector.com/content/images/87/f3/24/87f3244f3c5f350faa267d5e656320dd345f02fadf6a05f69a6029ff277d1071.jpg",
            "nameClear": "",
            "numeroLiga": "(35/51)",
            "codigoLiga": "chansey (35/51)",
            "myp": "",
            "language": "ja",
            "regulationMark": "",
            "retreatCost": 0
        },
        {
            "id": "6168",
            "name": "Kangaskhan",
            "nomePt": "",
            "collectionId": "smm-j",
            "supertypeId": 1,
            "rarityId": 10,
            "artistId": 149,
            "hp": 120,
            "number": "",
            "numberInt": 36,
            "smallImage": "https://static.tcgcollector.com/content/images/7b/2b/78/7b2b78f52bf25eeee248e9cfc4a15629116b0a30daaec2d00e42d506e120de72.jpg",
            "largeImage": "https://static.tcgcollector.com/content/images/7b/2b/78/7b2b78f52bf25eeee248e9cfc4a15629116b0a30daaec2d00e42d506e120de72.jpg",
            "nameClear": "",
            "numeroLiga": "(36/51)",
            "codigoLiga": "kangaskhan (36/51)",
            "myp": "",
            "language": "ja",
            "regulationMark": "",
            "retreatCost": 0
        },
        {
            "id": "6169",
            "name": "Eevee",
            "nomePt": "",
            "collectionId": "smm-j",
            "supertypeId": 1,
            "rarityId": 10,
            "artistId": 148,
            "hp": 60,
            "number": "",
            "numberInt": 37,
            "smallImage": "https://static.tcgcollector.com/content/images/50/06/55/500655926c49bb2d8a44e0acaf9538923642e4809434b44878f5c9d4456023e4.jpg",
            "largeImage": "https://static.tcgcollector.com/content/images/50/06/55/500655926c49bb2d8a44e0acaf9538923642e4809434b44878f5c9d4456023e4.jpg",
            "nameClear": "",
            "numeroLiga": "(37/51)",
            "codigoLiga": "eevee (37/51)",
            "myp": "",
            "language": "ja",
            "regulationMark": "",
            "retreatCost": 0
        },
        {
            "id": "6170",
            "name": "Snorlax",
            "nomePt": "",
            "collectionId": "smm-j",
            "supertypeId": 1,
            "rarityId": 10,
            "artistId": 130,
            "hp": 150,
            "number": "",
            "numberInt": 38,
            "smallImage": "https://static.tcgcollector.com/content/images/f2/bc/d1/f2bcd11d83c50d46d3ef5297faebacd36718a66a3959bbb92e7bdfbed522015e.jpg",
            "largeImage": "https://static.tcgcollector.com/content/images/f2/bc/d1/f2bcd11d83c50d46d3ef5297faebacd36718a66a3959bbb92e7bdfbed522015e.jpg",
            "nameClear": "",
            "numeroLiga": "(38/51)",
            "codigoLiga": "snorlax (38/51)",
            "myp": "",
            "language": "ja",
            "regulationMark": "",
            "retreatCost": 0
        },
        {
            "id": "6171",
            "name": "Potion",
            "nomePt": "",
            "collectionId": "smm-j",
            "supertypeId": 2,
            "rarityId": 10,
            "artistId": 132,
            "hp": 0,
            "number": "",
            "numberInt": 39,
            "smallImage": "https://static.tcgcollector.com/content/images/40/b8/7c/40b87c3325bc696adc25f069dfc21b56cf917720d4169075d16769dc1a56172a.jpg",
            "largeImage": "https://static.tcgcollector.com/content/images/40/b8/7c/40b87c3325bc696adc25f069dfc21b56cf917720d4169075d16769dc1a56172a.jpg",
            "nameClear": "",
            "numeroLiga": "(39/51)",
            "codigoLiga": "potion (39/51)",
            "myp": "",
            "language": "ja",
            "regulationMark": "",
            "retreatCost": 0
        },
        {
            "id": "6172",
            "name": "Crushing Hammer",
            "nomePt": "",
            "collectionId": "smm-j",
            "supertypeId": 2,
            "rarityId": 10,
            "artistId": 152,
            "hp": 0,
            "number": "",
            "numberInt": 40,
            "smallImage": "https://static.tcgcollector.com/content/images/03/ae/ca/03aeca6e116c41bc87333f1fa2c7efefe55c3775ab7162f590512d27ad488cbd.jpg",
            "largeImage": "https://static.tcgcollector.com/content/images/03/ae/ca/03aeca6e116c41bc87333f1fa2c7efefe55c3775ab7162f590512d27ad488cbd.jpg",
            "nameClear": "",
            "numeroLiga": "(40/51)",
            "codigoLiga": "crushing hammer (40/51)",
            "myp": "",
            "language": "ja",
            "regulationMark": "",
            "retreatCost": 0
        },
        {
            "id": "6173",
            "name": "Great Ball",
            "nomePt": "",
            "collectionId": "smm-j",
            "supertypeId": 2,
            "rarityId": 10,
            "artistId": 69,
            "hp": 0,
            "number": "",
            "numberInt": 41,
            "smallImage": "https://static.tcgcollector.com/content/images/6f/b3/92/6fb39247f4c24b46a8d21ff542f56a42853d68bc2bdd4fb3b85648ec22f35e41.jpg",
            "largeImage": "https://static.tcgcollector.com/content/images/6f/b3/92/6fb39247f4c24b46a8d21ff542f56a42853d68bc2bdd4fb3b85648ec22f35e41.jpg",
            "nameClear": "",
            "numeroLiga": "(41/51)",
            "codigoLiga": "great ball (41/51)",
            "myp": "",
            "language": "ja",
            "regulationMark": "",
            "retreatCost": 0
        },
        {
            "id": "6174",
            "name": "Rare Candy",
            "nomePt": "",
            "collectionId": "smm-j",
            "supertypeId": 2,
            "rarityId": 10,
            "artistId": 132,
            "hp": 0,
            "number": "",
            "numberInt": 42,
            "smallImage": "https://static.tcgcollector.com/content/images/99/fc/33/99fc332603442b384fda6e75a86d56a625e6a025c74f59178ad1423c5d9e10e3.jpg",
            "largeImage": "https://static.tcgcollector.com/content/images/99/fc/33/99fc332603442b384fda6e75a86d56a625e6a025c74f59178ad1423c5d9e10e3.jpg",
            "nameClear": "",
            "numeroLiga": "(42/51)",
            "codigoLiga": "rare candy (42/51)",
            "myp": "",
            "language": "ja",
            "regulationMark": "",
            "retreatCost": 0
        },
        {
            "id": "6175",
            "name": "Switch",
            "nomePt": "",
            "collectionId": "smm-j",
            "supertypeId": 2,
            "rarityId": 10,
            "artistId": 69,
            "hp": 0,
            "number": "",
            "numberInt": 43,
            "smallImage": "https://static.tcgcollector.com/content/images/7f/53/a3/7f53a30f0d973aa6a4f0fa9cd36f271f7fc19cf26c5ebe0a969adbb567a643af.jpg",
            "largeImage": "https://static.tcgcollector.com/content/images/7f/53/a3/7f53a30f0d973aa6a4f0fa9cd36f271f7fc19cf26c5ebe0a969adbb567a643af.jpg",
            "nameClear": "",
            "numeroLiga": "(43/51)",
            "codigoLiga": "switch (43/51)",
            "myp": "",
            "language": "ja",
            "regulationMark": "",
            "retreatCost": 0
        },
        {
            "id": "6176",
            "name": "Pokémon Catcher",
            "nomePt": "",
            "collectionId": "smm-j",
            "supertypeId": 2,
            "rarityId": 10,
            "artistId": 132,
            "hp": 0,
            "number": "",
            "numberInt": 44,
            "smallImage": "https://static.tcgcollector.com/content/images/58/c4/73/58c4732d8bcfb9432d6eccfb2da1d699808780644ae17de9a18d2d7f64ca9e0f.jpg",
            "largeImage": "https://static.tcgcollector.com/content/images/58/c4/73/58c4732d8bcfb9432d6eccfb2da1d699808780644ae17de9a18d2d7f64ca9e0f.jpg",
            "nameClear": "",
            "numeroLiga": "(44/51)",
            "codigoLiga": "pokémon catcher (44/51)",
            "myp": "",
            "language": "ja",
            "regulationMark": "",
            "retreatCost": 0
        },
        {
            "id": "6177",
            "name": "Ilima",
            "nomePt": "",
            "collectionId": "smm-j",
            "supertypeId": 2,
            "rarityId": 10,
            "artistId": 1,
            "hp": 0,
            "number": "",
            "numberInt": 45,
            "smallImage": "https://static.tcgcollector.com/content/images/d7/e4/91/d7e491ccf4e0347545829840bdd8126fc6c472a3f67606a2b16d06ccbcb82d30.jpg",
            "largeImage": "https://static.tcgcollector.com/content/images/d7/e4/91/d7e491ccf4e0347545829840bdd8126fc6c472a3f67606a2b16d06ccbcb82d30.jpg",
            "nameClear": "",
            "numeroLiga": "(45/51)",
            "codigoLiga": "ilima (45/51)",
            "myp": "",
            "language": "ja",
            "regulationMark": "",
            "retreatCost": 0
        },
        {
            "id": "6178",
            "name": "Professor Kukui",
            "nomePt": "",
            "collectionId": "smm-j",
            "supertypeId": 2,
            "rarityId": 10,
            "artistId": 1,
            "hp": 0,
            "number": "",
            "numberInt": 46,
            "smallImage": "https://static.tcgcollector.com/content/images/3a/ff/61/3aff61d84c7d4b72f684430aecd9a2d24b85a8f26c4bf60d1f3a0b2c432e71f5.jpg",
            "largeImage": "https://static.tcgcollector.com/content/images/3a/ff/61/3aff61d84c7d4b72f684430aecd9a2d24b85a8f26c4bf60d1f3a0b2c432e71f5.jpg",
            "nameClear": "",
            "numeroLiga": "(46/51)",
            "codigoLiga": "professor kukui (46/51)",
            "myp": "",
            "language": "ja",
            "regulationMark": "",
            "retreatCost": 0
        },
        {
            "id": "6179",
            "name": "Judge",
            "nomePt": "",
            "collectionId": "smm-j",
            "supertypeId": 2,
            "rarityId": 10,
            "artistId": 146,
            "hp": 0,
            "number": "",
            "numberInt": 47,
            "smallImage": "https://static.tcgcollector.com/content/images/2e/1c/53/2e1c53a56a5cf580d2befe820fbf87df5350f9b7158b46581e263b6188ecc93c.jpg",
            "largeImage": "https://static.tcgcollector.com/content/images/2e/1c/53/2e1c53a56a5cf580d2befe820fbf87df5350f9b7158b46581e263b6188ecc93c.jpg",
            "nameClear": "",
            "numeroLiga": "(47/51)",
            "codigoLiga": "judge (47/51)",
            "myp": "",
            "language": "ja",
            "regulationMark": "",
            "retreatCost": 0
        },
        {
            "id": "6180",
            "name": "Cynthia",
            "nomePt": "",
            "collectionId": "smm-j",
            "supertypeId": 2,
            "rarityId": 10,
            "artistId": 1,
            "hp": 0,
            "number": "",
            "numberInt": 48,
            "smallImage": "https://static.tcgcollector.com/content/images/32/49/84/32498493208e1b32a56522e3ec0373694df43720fb8f33154655d1a42e34a710.jpg",
            "largeImage": "https://static.tcgcollector.com/content/images/32/49/84/32498493208e1b32a56522e3ec0373694df43720fb8f33154655d1a42e34a710.jpg",
            "nameClear": "",
            "numeroLiga": "(48/51)",
            "codigoLiga": "cynthia (48/51)",
            "myp": "",
            "language": "ja",
            "regulationMark": "",
            "retreatCost": 0
        },
        {
            "id": "6181",
            "name": "Hau",
            "nomePt": "",
            "collectionId": "smm-j",
            "supertypeId": 2,
            "rarityId": 10,
            "artistId": 1,
            "hp": 0,
            "number": "",
            "numberInt": 49,
            "smallImage": "https://static.tcgcollector.com/content/images/f4/bc/34/f4bc3417587f4632a4fe539e73d0d914dd284633499b50ac2896551df8869a0a.jpg",
            "largeImage": "https://static.tcgcollector.com/content/images/f4/bc/34/f4bc3417587f4632a4fe539e73d0d914dd284633499b50ac2896551df8869a0a.jpg",
            "nameClear": "",
            "numeroLiga": "(49/51)",
            "codigoLiga": "hau (49/51)",
            "myp": "",
            "language": "ja",
            "regulationMark": "",
            "retreatCost": 0
        },
        {
            "id": "6182",
            "name": "Pokémon Center Lady",
            "nomePt": "",
            "collectionId": "smm-j",
            "supertypeId": 2,
            "rarityId": 10,
            "artistId": 107,
            "hp": 0,
            "number": "",
            "numberInt": 50,
            "smallImage": "https://static.tcgcollector.com/content/images/4f/8d/d8/4f8dd800835aaf6dd6c3d003dbeea9f468ec7b79003a5499c500453a4044f64e.jpg",
            "largeImage": "https://static.tcgcollector.com/content/images/4f/8d/d8/4f8dd800835aaf6dd6c3d003dbeea9f468ec7b79003a5499c500453a4044f64e.jpg",
            "nameClear": "",
            "numeroLiga": "(50/51)",
            "codigoLiga": "pokémon center lady (50/51)",
            "myp": "",
            "language": "ja",
            "regulationMark": "",
            "retreatCost": 0
        },
        {
            "id": "6183",
            "name": "Bug Catcher",
            "nomePt": "",
            "collectionId": "smm-j",
            "supertypeId": 2,
            "rarityId": 10,
            "artistId": 147,
            "hp": 0,
            "number": "",
            "numberInt": 51,
            "smallImage": "https://static.tcgcollector.com/content/images/7c/63/f6/7c63f69ce5ead7576e66939cf796049ee4570bdd49d559d32f8e0c9b4f7770bb.jpg",
            "largeImage": "https://static.tcgcollector.com/content/images/7c/63/f6/7c63f69ce5ead7576e66939cf796049ee4570bdd49d559d32f8e0c9b4f7770bb.jpg",
            "nameClear": "",
            "numeroLiga": "(51/51)",
            "codigoLiga": "bug catcher (51/51)",
            "myp": "",
            "language": "ja",
            "regulationMark": "",
            "retreatCost": 0
        }
    ]
}